wfs20/__init__.py
wfs20/_dbase.py
wfs20/crs.py
wfs20/error.py
wfs20/io.py
wfs20/reader.py
wfs20/request.py
wfs20/util.py
wfs20/version.py
wfs20/wfs.py
wfs20/data/axisorder.db
wfs20-0.2.2.dist-info/LICENSE
wfs20-0.2.2.dist-info/METADATA
wfs20-0.2.2.dist-info/WHEEL
wfs20-0.2.2.dist-info/top_level.txt
wfs20-0.2.2.dist-info/RECORD
