Metadata-Version: 2.1
Name: wfs20
Version: 0.2.2
Summary: Small library to request geospatial data (WFS)
Author-email: "B.W. Dalmijn" <brencodeert@outlook.com>
Maintainer-email: "B.W. Dalmijn" <brencodeert@outlook.com>
License: BSD
Project-URL: Homepage, https://github.com/B-Dalmijn/WFS20
Project-URL: Source, https://github.com/B-Dalmijn/WFS20
Project-URL: Tracker, https://github.com/B-Dalmijn/WFS20/issues
Keywords: wfs,GIS,request,vector
Classifier: Development Status :: 4 - Beta
Classifier: Intended Audience :: End Users/Desktop
Classifier: Intended Audience :: Developers
Classifier: Intended Audience :: Science/Research
Classifier: Topic :: Scientific/Engineering :: GIS
Classifier: License :: OSI Approved :: BSD License
Classifier: Natural Language :: English
Classifier: Operating System :: OS Independent
Classifier: Programming Language :: Python :: 3
Classifier: Programming Language :: Python :: 3.7
Classifier: Programming Language :: Python :: 3.8
Classifier: Programming Language :: Python :: 3.9
Classifier: Programming Language :: Python :: 3.10
Requires-Python: >=3.7
License-File: LICENSE
Requires-Dist: lxml
Requires-Dist: requests
Provides-Extra: dev
Requires-Dist: gdal (>=3.1) ; extra == 'dev'
Provides-Extra: test
Requires-Dist: black ; extra == 'test'
Requires-Dist: pytest (>=2.7.3) ; extra == 'test'
Requires-Dist: pytest-cov ; extra == 'test'
Requires-Dist: pytest-mock ; extra == 'test'
Requires-Dist: responses ; extra == 'test'
